{
    "Donation": [
        {
            "Note": "Thank you {option_user} For (`{raw.response.Donation.0.LongassThing}`)" ,
            "Note2": "You have Unlocked {raw.response.{option_tier}.0.Role}"
            "Hold": "dominator07509 Hold's The Items",
            "if": "(Role Given)",
            "amount": "{option_item-gave}",
            "LongassThing": "{raw.response.Donation.0.amount}"
        }
    ],
    "bronse-(I)": [
        {
            "Role": "<@&1333309052163457065>",
            "name": "1333309052163457065",
            "amount": "???"
        }
    ],
    "silver-(II)": [
        {
            "Role": "<@&1333309702339297332>",
            "name": "1333309702339297332",
            "amount": "???"
        }
    ],
    "gold-(III)": [
        {
            "Role": "<@&1333310872176689213>",
            "name": "1333310872176689213",
            "amount": "???"
        }
    ],
    "imperial-(IV)": [
        {
            "Role": "<@&1333311132873523275>",
            "name": "1333311132873523275",
            "amount": "???"
        }
    ],
    "Dom-og-(V)": [
        {
            "Role": "<@&1333311133976891462>",
            "name": "1333311133976891462",
            "amount": "???"
        }
    ],
    "No-Role": [
        {
            "Role": "`Sorry not a enough For the Next Role`",
            "name": "1299636672396394557",
            "amount": "???"
        }
    ]
}
